{
  "openapi": "3.0.1",
  "info": {
    "title": "ExamNest",
    "version": "1.0"
  },
  "paths": {
    "/api/Access/me": {
      "get": {
        "tags": [
          "Access"
        ],
        "responses": {
          "200": {
            "description": "OK"
          }
        }
      }
    },
    "/api/Access/admin": {
      "get": {
        "tags": [
          "Access"
        ],
        "responses": {
          "200": {
            "description": "OK"
          }
        }
      }
    },
    "/api/Access/teacher": {
      "get": {
        "tags": [
          "Access"
        ],
        "responses": {
          "200": {
            "description": "OK"
          }
        }
      }
    },
    "/api/Access/student": {
      "get": {
        "tags": [
          "Access"
        ],
        "responses": {
          "200": {
            "description": "OK"
          }
        }
      }
    },
    "/api/Admin/GetAllTeacher": {
      "get": {
        "tags": [
          "Admin"
        ],
        "parameters": [
          {
            "name": "search",
            "in": "query",
            "schema": {
              "type": "string"
            }
          }
        ],
        "responses": {
          "200": {
            "description": "OK"
          }
        }
      }
    },
    "/api/Admin/GetAllStudent": {
      "get": {
        "tags": [
          "Admin"
        ],
        "parameters": [
          {
            "name": "search",
            "in": "query",
            "schema": {
              "type": "string"
            }
          }
        ],
        "responses": {
          "200": {
            "description": "OK"
          }
        }
      }
    },
    "/api/Admin/GetUserById/{id}": {
      "get": {
        "tags": [
          "Admin"
        ],
        "parameters": [
          {
            "name": "id",
            "in": "path",
            "required": true,
            "schema": {
              "type": "integer",
              "format": "int32"
            }
          }
        ],
        "responses": {
          "200": {
            "description": "OK"
          }
        }
      }
    },
    "/api/Admin/CreateUser/AddTeacher": {
      "post": {
        "tags": [
          "Admin"
        ],
        "requestBody": {
          "content": {
            "application/json": {
              "schema": {
                "$ref": "#/components/schemas/UserCreateDTO"
              }
            },
            "text/json": {
              "schema": {
                "$ref": "#/components/schemas/UserCreateDTO"
              }
            },
            "application/*+json": {
              "schema": {
                "$ref": "#/components/schemas/UserCreateDTO"
              }
            }
          }
        },
        "responses": {
          "200": {
            "description": "OK"
          }
        }
      }
    },
    "/api/Admin/UpdateUser/{id}": {
      "put": {
        "tags": [
          "Admin"
        ],
        "parameters": [
          {
            "name": "id",
            "in": "path",
            "required": true,
            "schema": {
              "type": "integer",
              "format": "int32"
            }
          }
        ],
        "requestBody": {
          "content": {
            "application/json": {
              "schema": {
                "$ref": "#/components/schemas/UserUpdateDTO"
              }
            },
            "text/json": {
              "schema": {
                "$ref": "#/components/schemas/UserUpdateDTO"
              }
            },
            "application/*+json": {
              "schema": {
                "$ref": "#/components/schemas/UserUpdateDTO"
              }
            }
          }
        },
        "responses": {
          "200": {
            "description": "OK"
          }
        }
      }
    },
    "/api/Admin/UpdateStudent/{id}": {
      "put": {
        "tags": [
          "Admin"
        ],
        "parameters": [
          {
            "name": "id",
            "in": "path",
            "required": true,
            "schema": {
              "type": "integer",
              "format": "int32"
            }
          }
        ],
        "requestBody": {
          "content": {
            "application/json": {
              "schema": {
                "$ref": "#/components/schemas/UserUpdateDTO"
              }
            },
            "text/json": {
              "schema": {
                "$ref": "#/components/schemas/UserUpdateDTO"
              }
            },
            "application/*+json": {
              "schema": {
                "$ref": "#/components/schemas/UserUpdateDTO"
              }
            }
          }
        },
        "responses": {
          "200": {
            "description": "OK"
          }
        }
      }
    },
    "/api/Admin/DeleteUser/{id}": {
      "delete": {
        "tags": [
          "Admin"
        ],
        "parameters": [
          {
            "name": "id",
            "in": "path",
            "required": true,
            "schema": {
              "type": "integer",
              "format": "int32"
            }
          }
        ],
        "responses": {
          "200": {
            "description": "OK"
          }
        }
      }
    },
    "/api/Admin/DeleteStudent/{id}": {
      "delete": {
        "tags": [
          "Admin"
        ],
        "parameters": [
          {
            "name": "id",
            "in": "path",
            "required": true,
            "schema": {
              "type": "integer",
              "format": "int32"
            }
          }
        ],
        "responses": {
          "200": {
            "description": "OK"
          }
        }
      }
    },
    "/api/Admin/GetAllCourses": {
      "get": {
        "tags": [
          "Admin"
        ],
        "parameters": [
          {
            "name": "search",
            "in": "query",
            "schema": {
              "type": "string"
            }
          }
        ],
        "responses": {
          "200": {
            "description": "OK"
          }
        }
      }
    },
    "/api/Admin/GlobalSearch": {
      "get": {
        "tags": [
          "Admin"
        ],
        "parameters": [
          {
            "name": "q",
            "in": "query",
            "schema": {
              "type": "string"
            }
          },
          {
            "name": "take",
            "in": "query",
            "schema": {
              "type": "integer",
              "format": "int32",
              "default": 5
            }
          }
        ],
        "responses": {
          "200": {
            "description": "OK"
          }
        }
      }
    },
    "/api/Admin/GetSuggestions/suggestions": {
      "get": {
        "tags": [
          "Admin"
        ],
        "parameters": [
          {
            "name": "status",
            "in": "query",
            "schema": {
              "type": "string"
            }
          }
        ],
        "responses": {
          "200": {
            "description": "OK"
          }
        }
      }
    },
    "/api/Admin/PublishCourse": {
      "post": {
        "tags": [
          "Admin"
        ],
        "requestBody": {
          "content": {
            "application/json": {
              "schema": {
                "type": "integer",
                "format": "int32"
              }
            },
            "text/json": {
              "schema": {
                "type": "integer",
                "format": "int32"
              }
            },
            "application/*+json": {
              "schema": {
                "type": "integer",
                "format": "int32"
              }
            }
          }
        },
        "responses": {
          "200": {
            "description": "OK"
          }
        }
      }
    },
    "/api/Admin/DeleteCourseWiseId/courses/{courseId}/delete": {
      "post": {
        "tags": [
          "Admin"
        ],
        "parameters": [
          {
            "name": "courseId",
            "in": "path",
            "required": true,
            "schema": {
              "type": "integer",
              "format": "int32"
            }
          }
        ],
        "responses": {
          "200": {
            "description": "OK"
          }
        }
      }
    },
    "/api/Admin/GetLiveClasses": {
      "get": {
        "tags": [
          "Admin"
        ],
        "parameters": [
          {
            "name": "courseId",
            "in": "query",
            "schema": {
              "type": "integer",
              "format": "int32"
            }
          }
        ],
        "responses": {
          "200": {
            "description": "OK"
          }
        }
      }
    },
    "/api/Admin/CreateLiveClass": {
      "post": {
        "tags": [
          "Admin"
        ],
        "requestBody": {
          "content": {
            "application/json": {
              "schema": {
                "$ref": "#/components/schemas/LiveClassCreateDto"
              }
            },
            "text/json": {
              "schema": {
                "$ref": "#/components/schemas/LiveClassCreateDto"
              }
            },
            "application/*+json": {
              "schema": {
                "$ref": "#/components/schemas/LiveClassCreateDto"
              }
            }
          }
        },
        "responses": {
          "200": {
            "description": "OK"
          }
        }
      }
    },
    "/api/Admin/DeleteLiveClass/{id}": {
      "delete": {
        "tags": [
          "Admin"
        ],
        "parameters": [
          {
            "name": "id",
            "in": "path",
            "required": true,
            "schema": {
              "type": "integer",
              "format": "int32"
            }
          }
        ],
        "responses": {
          "200": {
            "description": "OK"
          }
        }
      }
    },
    "/api/Admin/GetAllPayments/payments": {
      "get": {
        "tags": [
          "Admin"
        ],
        "responses": {
          "200": {
            "description": "OK"
          }
        }
      }
    },
    "/api/Admin/GetPaymentDetail/payments/{id}": {
      "get": {
        "tags": [
          "Admin"
        ],
        "parameters": [
          {
            "name": "id",
            "in": "path",
            "required": true,
            "schema": {
              "type": "integer",
              "format": "int32"
            }
          }
        ],
        "responses": {
          "200": {
            "description": "OK"
          }
        }
      }
    },
    "/api/Admin/CheckPayment/payments/check/{paymentId}": {
      "get": {
        "tags": [
          "Admin"
        ],
        "parameters": [
          {
            "name": "paymentId",
            "in": "path",
            "required": true,
            "schema": {
              "type": "string"
            }
          }
        ],
        "responses": {
          "200": {
            "description": "OK"
          }
        }
      }
    },
    "/api/Admin/GetAllExams/exams": {
      "get": {
        "tags": [
          "Admin"
        ],
        "responses": {
          "200": {
            "description": "OK"
          }
        }
      }
    },
    "/api/Admin/DeleteExam/exams/{id}": {
      "delete": {
        "tags": [
          "Admin"
        ],
        "parameters": [
          {
            "name": "id",
            "in": "path",
            "required": true,
            "schema": {
              "type": "integer",
              "format": "int32"
            }
          }
        ],
        "responses": {
          "200": {
            "description": "OK"
          }
        }
      }
    },
    "/api/Admin/GetStudentsByExam/exams/{examId}/students": {
      "get": {
        "tags": [
          "Admin"
        ],
        "parameters": [
          {
            "name": "examId",
            "in": "path",
            "required": true,
            "schema": {
              "type": "integer",
              "format": "int32"
            }
          }
        ],
        "responses": {
          "200": {
            "description": "OK"
          }
        }
      }
    },
    "/api/Admin/GetRoles": {
      "get": {
        "tags": [
          "Admin"
        ],
        "responses": {
          "200": {
            "description": "OK"
          }
        }
      }
    },
    "/api/Admin/GetRole/{id}": {
      "get": {
        "tags": [
          "Admin"
        ],
        "parameters": [
          {
            "name": "id",
            "in": "path",
            "required": true,
            "schema": {
              "type": "integer",
              "format": "int32"
            }
          }
        ],
        "responses": {
          "200": {
            "description": "OK"
          }
        }
      }
    },
    "/api/Admin/CreateRole": {
      "post": {
        "tags": [
          "Admin"
        ],
        "requestBody": {
          "content": {
            "application/json": {
              "schema": {
                "$ref": "#/components/schemas/Role"
              }
            },
            "text/json": {
              "schema": {
                "$ref": "#/components/schemas/Role"
              }
            },
            "application/*+json": {
              "schema": {
                "$ref": "#/components/schemas/Role"
              }
            }
          }
        },
        "responses": {
          "200": {
            "description": "OK"
          }
        }
      }
    },
    "/api/Admin/UpdateRole/{id}": {
      "put": {
        "tags": [
          "Admin"
        ],
        "parameters": [
          {
            "name": "id",
            "in": "path",
            "required": true,
            "schema": {
              "type": "integer",
              "format": "int32"
            }
          }
        ],
        "requestBody": {
          "content": {
            "application/json": {
              "schema": {
                "$ref": "#/components/schemas/Role"
              }
            },
            "text/json": {
              "schema": {
                "$ref": "#/components/schemas/Role"
              }
            },
            "application/*+json": {
              "schema": {
                "$ref": "#/components/schemas/Role"
              }
            }
          }
        },
        "responses": {
          "200": {
            "description": "OK"
          }
        }
      }
    },
    "/api/Admin/DeleteRole/{id}": {
      "delete": {
        "tags": [
          "Admin"
        ],
        "parameters": [
          {
            "name": "id",
            "in": "path",
            "required": true,
            "schema": {
              "type": "integer",
              "format": "int32"
            }
          }
        ],
        "responses": {
          "200": {
            "description": "OK"
          }
        }
      }
    },
    "/api/Admin/GetDashboardData/dashboarddata": {
      "get": {
        "tags": [
          "Admin"
        ],
        "responses": {
          "200": {
            "description": "OK"
          }
        }
      }
    },
    "/api/Admin/GetTopExams/top-exams": {
      "get": {
        "tags": [
          "Admin"
        ],
        "responses": {
          "200": {
            "description": "OK"
          }
        }
      }
    },
    "/api/Admin/GetCourseByid/CourseById/{CourseId}": {
      "get": {
        "tags": [
          "Admin"
        ],
        "parameters": [
          {
            "name": "CourseId",
            "in": "path",
            "required": true,
            "schema": {
              "type": "integer",
              "format": "int32"
            }
          }
        ],
        "responses": {
          "200": {
            "description": "OK"
          }
        }
      }
    },
    "/api/Admin/GetUserProfile/MyProfile": {
      "get": {
        "tags": [
          "Admin"
        ],
        "responses": {
          "200": {
            "description": "OK"
          }
        }
      }
    },
    "/api/Admin/UpdateProfile/profile/update": {
      "post": {
        "tags": [
          "Admin"
        ],
        "requestBody": {
          "content": {
            "application/json": {
              "schema": {
                "$ref": "#/components/schemas/UpdateProfileDto"
              }
            },
            "text/json": {
              "schema": {
                "$ref": "#/components/schemas/UpdateProfileDto"
              }
            },
            "application/*+json": {
              "schema": {
                "$ref": "#/components/schemas/UpdateProfileDto"
              }
            }
          }
        },
        "responses": {
          "200": {
            "description": "OK"
          }
        }
      }
    },
    "/api/Admin/UploadProfileImage/profile/upload-image": {
      "post": {
        "tags": [
          "Admin"
        ],
        "requestBody": {
          "content": {
            "multipart/form-data": {
              "schema": {
                "type": "object",
                "properties": {
                  "ProfileImage": {
                    "type": "string",
                    "format": "binary"
                  }
                }
              },
              "encoding": {
                "ProfileImage": {
                  "style": "form"
                }
              }
            }
          }
        },
        "responses": {
          "200": {
            "description": "OK"
          }
        }
      }
    },
    "/api/Admin/GetCourseEarnings/course-earnings": {
      "get": {
        "tags": [
          "Admin"
        ],
        "responses": {
          "200": {
            "description": "OK"
          }
        }
      }
    },
    "/api/Auth/register": {
      "post": {
        "tags": [
          "Auth"
        ],
        "requestBody": {
          "content": {
            "application/json": {
              "schema": {
                "$ref": "#/components/schemas/RegisterRequestDto"
              }
            },
            "text/json": {
              "schema": {
                "$ref": "#/components/schemas/RegisterRequestDto"
              }
            },
            "application/*+json": {
              "schema": {
                "$ref": "#/components/schemas/RegisterRequestDto"
              }
            }
          }
        },
        "responses": {
          "200": {
            "description": "OK"
          }
        }
      }
    },
    "/api/Auth/login": {
      "post": {
        "tags": [
          "Auth"
        ],
        "requestBody": {
          "content": {
            "application/json": {
              "schema": {
                "$ref": "#/components/schemas/LoginRequestDto"
              }
            },
            "text/json": {
              "schema": {
                "$ref": "#/components/schemas/LoginRequestDto"
              }
            },
            "application/*+json": {
              "schema": {
                "$ref": "#/components/schemas/LoginRequestDto"
              }
            }
          }
        },
        "responses": {
          "200": {
            "description": "OK"
          }
        }
      }
    },
    "/api/Auth/verify-email-otp": {
      "post": {
        "tags": [
          "Auth"
        ],
        "requestBody": {
          "content": {
            "application/json": {
              "schema": {
                "$ref": "#/components/schemas/VerifyEmailOtpRequestDto"
              }
            },
            "text/json": {
              "schema": {
                "$ref": "#/components/schemas/VerifyEmailOtpRequestDto"
              }
            },
            "application/*+json": {
              "schema": {
                "$ref": "#/components/schemas/VerifyEmailOtpRequestDto"
              }
            }
          }
        },
        "responses": {
          "200": {
            "description": "OK"
          }
        }
      }
    },
    "/api/Auth/resend-email-otp": {
      "post": {
        "tags": [
          "Auth"
        ],
        "requestBody": {
          "content": {
            "application/json": {
              "schema": {
                "$ref": "#/components/schemas/ResendEmailOtpRequestDto"
              }
            },
            "text/json": {
              "schema": {
                "$ref": "#/components/schemas/ResendEmailOtpRequestDto"
              }
            },
            "application/*+json": {
              "schema": {
                "$ref": "#/components/schemas/ResendEmailOtpRequestDto"
              }
            }
          }
        },
        "responses": {
          "200": {
            "description": "OK"
          }
        }
      }
    },
    "/api/Auth/forgot-password": {
      "post": {
        "tags": [
          "Auth"
        ],
        "requestBody": {
          "content": {
            "application/json": {
              "schema": {
                "$ref": "#/components/schemas/ForgotPasswordRequestDto"
              }
            },
            "text/json": {
              "schema": {
                "$ref": "#/components/schemas/ForgotPasswordRequestDto"
              }
            },
            "application/*+json": {
              "schema": {
                "$ref": "#/components/schemas/ForgotPasswordRequestDto"
              }
            }
          }
        },
        "responses": {
          "200": {
            "description": "OK"
          }
        }
      }
    },
    "/api/Auth/verify-forgot-password-otp": {
      "post": {
        "tags": [
          "Auth"
        ],
        "requestBody": {
          "content": {
            "application/json": {
              "schema": {
                "$ref": "#/components/schemas/VerifyForgotPasswordOtpRequestDto"
              }
            },
            "text/json": {
              "schema": {
                "$ref": "#/components/schemas/VerifyForgotPasswordOtpRequestDto"
              }
            },
            "application/*+json": {
              "schema": {
                "$ref": "#/components/schemas/VerifyForgotPasswordOtpRequestDto"
              }
            }
          }
        },
        "responses": {
          "200": {
            "description": "OK"
          }
        }
      }
    },
    "/api/Auth/reset-password": {
      "post": {
        "tags": [
          "Auth"
        ],
        "requestBody": {
          "content": {
            "application/json": {
              "schema": {
                "$ref": "#/components/schemas/ResetPasswordRequestDto"
              }
            },
            "text/json": {
              "schema": {
                "$ref": "#/components/schemas/ResetPasswordRequestDto"
              }
            },
            "application/*+json": {
              "schema": {
                "$ref": "#/components/schemas/ResetPasswordRequestDto"
              }
            }
          }
        },
        "responses": {
          "200": {
            "description": "OK"
          }
        }
      }
    },
    "/api/Auth/google-login": {
      "post": {
        "tags": [
          "Auth"
        ],
        "requestBody": {
          "content": {
            "application/json": {
              "schema": {
                "$ref": "#/components/schemas/GoogleLoginRequestDto"
              }
            },
            "text/json": {
              "schema": {
                "$ref": "#/components/schemas/GoogleLoginRequestDto"
              }
            },
            "application/*+json": {
              "schema": {
                "$ref": "#/components/schemas/GoogleLoginRequestDto"
              }
            }
          }
        },
        "responses": {
          "200": {
            "description": "OK"
          }
        }
      }
    },
    "/api/Auth/google-client-id": {
      "get": {
        "tags": [
          "Auth"
        ],
        "responses": {
          "200": {
            "description": "OK"
          }
        }
      }
    },
    "/api/Chatbot/ask": {
      "post": {
        "tags": [
          "Chatbot"
        ],
        "requestBody": {
          "content": {
            "application/json": {
              "schema": {
                "$ref": "#/components/schemas/ChatbotAskRequest"
              }
            },
            "text/json": {
              "schema": {
                "$ref": "#/components/schemas/ChatbotAskRequest"
              }
            },
            "application/*+json": {
              "schema": {
                "$ref": "#/components/schemas/ChatbotAskRequest"
              }
            }
          }
        },
        "responses": {
          "200": {
            "description": "OK"
          }
        }
      }
    },
    "/api/Exam/GetTeacherWiseCourse": {
      "get": {
        "tags": [
          "Exam"
        ],
        "responses": {
          "200": {
            "description": "OK"
          }
        }
      }
    },
    "/api/Exam/PublishResult/publish-result/{examId}": {
      "put": {
        "tags": [
          "Exam"
        ],
        "parameters": [
          {
            "name": "examId",
            "in": "path",
            "required": true,
            "schema": {
              "type": "integer",
              "format": "int32"
            }
          }
        ],
        "responses": {
          "200": {
            "description": "OK"
          }
        }
      }
    },
    "/api/Payment/create-order": {
      "post": {
        "tags": [
          "Payment"
        ],
        "requestBody": {
          "content": {
            "application/json": {
              "schema": {
                "$ref": "#/components/schemas/CreateOrderRequest"
              }
            },
            "text/json": {
              "schema": {
                "$ref": "#/components/schemas/CreateOrderRequest"
              }
            },
            "application/*+json": {
              "schema": {
                "$ref": "#/components/schemas/CreateOrderRequest"
              }
            }
          }
        },
        "responses": {
          "200": {
            "description": "OK"
          }
        }
      }
    },
    "/api/Payment/verify-payment": {
      "post": {
        "tags": [
          "Payment"
        ],
        "requestBody": {
          "content": {
            "application/json": {
              "schema": {
                "$ref": "#/components/schemas/VerifyPaymentRequest"
              }
            },
            "text/json": {
              "schema": {
                "$ref": "#/components/schemas/VerifyPaymentRequest"
              }
            },
            "application/*+json": {
              "schema": {
                "$ref": "#/components/schemas/VerifyPaymentRequest"
              }
            }
          }
        },
        "responses": {
          "200": {
            "description": "OK"
          }
        }
      }
    },
    "/api/Student/published-courses": {
      "get": {
        "tags": [
          "Student"
        ],
        "parameters": [
          {
            "name": "search",
            "in": "query",
            "schema": {
              "type": "string"
            }
          }
        ],
        "responses": {
          "200": {
            "description": "OK"
          }
        }
      }
    },
    "/api/Student/Get-Subscribed-course": {
      "get": {
        "tags": [
          "Student"
        ],
        "parameters": [
          {
            "name": "search",
            "in": "query",
            "schema": {
              "type": "string"
            }
          }
        ],
        "responses": {
          "200": {
            "description": "OK"
          }
        }
      }
    },
    "/api/Student/course/{courseId}/videos": {
      "get": {
        "tags": [
          "Student"
        ],
        "parameters": [
          {
            "name": "courseId",
            "in": "path",
            "required": true,
            "schema": {
              "type": "integer",
              "format": "int32"
            }
          }
        ],
        "responses": {
          "200": {
            "description": "OK"
          }
        }
      }
    },
    "/api/Student/course/{courseId}/access": {
      "get": {
        "tags": [
          "Student"
        ],
        "parameters": [
          {
            "name": "courseId",
            "in": "path",
            "required": true,
            "schema": {
              "type": "integer",
              "format": "int32"
            }
          }
        ],
        "responses": {
          "200": {
            "description": "OK"
          }
        }
      }
    },
    "/api/Student/GetCourseById": {
      "get": {
        "tags": [
          "Student"
        ],
        "parameters": [
          {
            "name": "courseId",
            "in": "query",
            "schema": {
              "type": "integer",
              "format": "int32"
            }
          }
        ],
        "responses": {
          "200": {
            "description": "OK"
          }
        }
      }
    },
    "/api/Student/live-classes": {
      "get": {
        "tags": [
          "Student"
        ],
        "responses": {
          "200": {
            "description": "OK"
          }
        }
      }
    },
    "/api/Student/my-exams": {
      "get": {
        "tags": [
          "Student"
        ],
        "responses": {
          "200": {
            "description": "OK"
          }
        }
      }
    },
    "/api/Student/exam/{examId}/start": {
      "post": {
        "tags": [
          "Student"
        ],
        "parameters": [
          {
            "name": "examId",
            "in": "path",
            "required": true,
            "schema": {
              "type": "integer",
              "format": "int32"
            }
          }
        ],
        "responses": {
          "200": {
            "description": "OK"
          }
        }
      }
    },
    "/api/Student/exam/{examId}/submit": {
      "post": {
        "tags": [
          "Student"
        ],
        "parameters": [
          {
            "name": "examId",
            "in": "path",
            "required": true,
            "schema": {
              "type": "integer",
              "format": "int32"
            }
          }
        ],
        "requestBody": {
          "content": {
            "application/json": {
              "schema": {
                "$ref": "#/components/schemas/SubmitExamRequestDto"
              }
            },
            "text/json": {
              "schema": {
                "$ref": "#/components/schemas/SubmitExamRequestDto"
              }
            },
            "application/*+json": {
              "schema": {
                "$ref": "#/components/schemas/SubmitExamRequestDto"
              }
            }
          }
        },
        "responses": {
          "200": {
            "description": "OK"
          }
        }
      }
    },
    "/api/Student/exam/{examId}/report-violation": {
      "post": {
        "tags": [
          "Student"
        ],
        "parameters": [
          {
            "name": "examId",
            "in": "path",
            "required": true,
            "schema": {
              "type": "integer",
              "format": "int32"
            }
          }
        ],
        "requestBody": {
          "content": {
            "application/json": {
              "schema": {
                "$ref": "#/components/schemas/ExamViolationRequestDto"
              }
            },
            "text/json": {
              "schema": {
                "$ref": "#/components/schemas/ExamViolationRequestDto"
              }
            },
            "application/*+json": {
              "schema": {
                "$ref": "#/components/schemas/ExamViolationRequestDto"
              }
            }
          }
        },
        "responses": {
          "200": {
            "description": "OK"
          }
        }
      }
    },
    "/api/Student/exam/{examId}/result/{attemptId}": {
      "get": {
        "tags": [
          "Student"
        ],
        "parameters": [
          {
            "name": "examId",
            "in": "path",
            "required": true,
            "schema": {
              "type": "integer",
              "format": "int32"
            }
          },
          {
            "name": "attemptId",
            "in": "path",
            "required": true,
            "schema": {
              "type": "integer",
              "format": "int32"
            }
          }
        ],
        "responses": {
          "200": {
            "description": "OK"
          }
        }
      }
    },
    "/api/Student/my-attempted-exams": {
      "get": {
        "tags": [
          "Student"
        ],
        "responses": {
          "200": {
            "description": "OK"
          }
        }
      }
    },
    "/api/Student/suggestion/post": {
      "post": {
        "tags": [
          "Student"
        ],
        "requestBody": {
          "content": {
            "application/json": {
              "schema": {
                "$ref": "#/components/schemas/SuggestionCreateDto"
              }
            },
            "text/json": {
              "schema": {
                "$ref": "#/components/schemas/SuggestionCreateDto"
              }
            },
            "application/*+json": {
              "schema": {
                "$ref": "#/components/schemas/SuggestionCreateDto"
              }
            }
          }
        },
        "responses": {
          "200": {
            "description": "OK"
          }
        }
      }
    },
    "/api/Student/my-teachers": {
      "get": {
        "tags": [
          "Student"
        ],
        "responses": {
          "200": {
            "description": "OK"
          }
        }
      }
    },
    "/api/Student/studentgetsuggestion": {
      "get": {
        "tags": [
          "Student"
        ],
        "responses": {
          "200": {
            "description": "OK"
          }
        }
      }
    },
    "/api/Student/student-dashboard": {
      "get": {
        "tags": [
          "Student"
        ],
        "responses": {
          "200": {
            "description": "OK"
          }
        }
      }
    },
    "/api/Student/student-courses": {
      "get": {
        "tags": [
          "Student"
        ],
        "responses": {
          "200": {
            "description": "OK"
          }
        }
      }
    },
    "/api/Student/student-exams": {
      "get": {
        "tags": [
          "Student"
        ],
        "responses": {
          "200": {
            "description": "OK"
          }
        }
      }
    },
    "/api/Student/student/last-7-days-scores": {
      "get": {
        "tags": [
          "Student"
        ],
        "responses": {
          "200": {
            "description": "OK"
          }
        }
      }
    },
    "/api/Teacher/CreateCourse/create": {
      "post": {
        "tags": [
          "Teacher"
        ],
        "requestBody": {
          "content": {
            "multipart/form-data": {
              "schema": {
                "type": "object",
                "properties": {
                  "Title": {
                    "type": "string"
                  },
                  "Description": {
                    "type": "string"
                  },
                  "Fees": {
                    "type": "number",
                    "format": "float"
                  },
                  "StartDate": {
                    "type": "string",
                    "format": "date-time"
                  },
                  "EndDate": {
                    "type": "string",
                    "format": "date-time"
                  },
                  "ThumbailUrl": {
                    "type": "string",
                    "format": "binary"
                  },
                  "Files": {
                    "type": "array",
                    "items": {
                      "type": "string",
                      "format": "binary"
                    }
                  }
                }
              },
              "encoding": {
                "Title": {
                  "style": "form"
                },
                "Description": {
                  "style": "form"
                },
                "Fees": {
                  "style": "form"
                },
                "StartDate": {
                  "style": "form"
                },
                "EndDate": {
                  "style": "form"
                },
                "ThumbailUrl": {
                  "style": "form"
                },
                "Files": {
                  "style": "form"
                }
              }
            }
          }
        },
        "responses": {
          "200": {
            "description": "OK"
          }
        }
      }
    },
    "/api/Teacher/GetMyCourses/mycourses": {
      "get": {
        "tags": [
          "Teacher"
        ],
        "responses": {
          "200": {
            "description": "OK"
          }
        }
      }
    },
    "/api/Teacher/UploadExamFromExcel/upload-exam-excel": {
      "post": {
        "tags": [
          "Teacher"
        ],
        "requestBody": {
          "content": {
            "multipart/form-data": {
              "schema": {
                "type": "object",
                "properties": {
                  "CourseId": {
                    "type": "integer",
                    "format": "int32"
                  },
                  "Title": {
                    "type": "string"
                  },
                  "Description": {
                    "type": "string"
                  },
                  "StartAt": {
                    "type": "string",
                    "format": "date-time"
                  },
                  "EndAt": {
                    "type": "string",
                    "format": "date-time"
                  },
                  "DurationMinutes": {
                    "type": "integer",
                    "format": "int32"
                  },
                  "RandomQuestionCount": {
                    "type": "integer",
                    "format": "int32"
                  },
                  "ExcelFile": {
                    "type": "string",
                    "format": "binary"
                  }
                }
              },
              "encoding": {
                "CourseId": {
                  "style": "form"
                },
                "Title": {
                  "style": "form"
                },
                "Description": {
                  "style": "form"
                },
                "StartAt": {
                  "style": "form"
                },
                "EndAt": {
                  "style": "form"
                },
                "DurationMinutes": {
                  "style": "form"
                },
                "RandomQuestionCount": {
                  "style": "form"
                },
                "ExcelFile": {
                  "style": "form"
                }
              }
            }
          }
        },
        "responses": {
          "200": {
            "description": "OK"
          }
        }
      }
    },
    "/api/Teacher/GetTotalCourses/GetTotalCourses": {
      "get": {
        "tags": [
          "Teacher"
        ],
        "responses": {
          "200": {
            "description": "OK"
          }
        }
      }
    },
    "/api/Teacher/GetTotalStudent/GetTotalStudent": {
      "get": {
        "tags": [
          "Teacher"
        ],
        "responses": {
          "200": {
            "description": "OK"
          }
        }
      }
    },
    "/api/Teacher/GetTotalExam/GetTotalExam": {
      "get": {
        "tags": [
          "Teacher"
        ],
        "responses": {
          "200": {
            "description": "OK"
          }
        }
      }
    },
    "/api/Teacher/GetTotalEarnings/GetTotalEarnings": {
      "get": {
        "tags": [
          "Teacher"
        ],
        "responses": {
          "200": {
            "description": "OK"
          }
        }
      }
    },
    "/api/Teacher/GetStudentsByCourse/course/{courseId}/students": {
      "get": {
        "tags": [
          "Teacher"
        ],
        "parameters": [
          {
            "name": "courseId",
            "in": "path",
            "required": true,
            "schema": {
              "type": "integer",
              "format": "int32"
            }
          }
        ],
        "responses": {
          "200": {
            "description": "OK"
          }
        }
      }
    },
    "/api/Teacher/GetStudentsByExam/exams/{examId}/students": {
      "get": {
        "tags": [
          "Teacher"
        ],
        "parameters": [
          {
            "name": "examId",
            "in": "path",
            "required": true,
            "schema": {
              "type": "integer",
              "format": "int32"
            }
          }
        ],
        "responses": {
          "200": {
            "description": "OK"
          }
        }
      }
    },
    "/api/Teacher/GetCourseDetail/{id}": {
      "get": {
        "tags": [
          "Teacher"
        ],
        "parameters": [
          {
            "name": "id",
            "in": "path",
            "required": true,
            "schema": {
              "type": "integer",
              "format": "int32"
            }
          }
        ],
        "responses": {
          "200": {
            "description": "OK"
          }
        }
      }
    },
    "/api/Teacher/DeleteCourse/delete-course/{id}": {
      "delete": {
        "tags": [
          "Teacher"
        ],
        "parameters": [
          {
            "name": "id",
            "in": "path",
            "required": true,
            "schema": {
              "type": "integer",
              "format": "int32"
            }
          }
        ],
        "responses": {
          "200": {
            "description": "OK"
          }
        }
      }
    },
    "/api/Teacher/UpdateCourse/{id}": {
      "put": {
        "tags": [
          "Teacher"
        ],
        "parameters": [
          {
            "name": "id",
            "in": "path",
            "required": true,
            "schema": {
              "type": "integer",
              "format": "int32"
            }
          }
        ],
        "requestBody": {
          "content": {
            "application/json": {
              "schema": {
                "$ref": "#/components/schemas/Course"
              }
            },
            "text/json": {
              "schema": {
                "$ref": "#/components/schemas/Course"
              }
            },
            "application/*+json": {
              "schema": {
                "$ref": "#/components/schemas/Course"
              }
            }
          }
        },
        "responses": {
          "200": {
            "description": "OK"
          }
        }
      }
    },
    "/api/Teacher/UploadMedia/media/upload/{courseId}": {
      "post": {
        "tags": [
          "Teacher"
        ],
        "parameters": [
          {
            "name": "courseId",
            "in": "path",
            "required": true,
            "schema": {
              "type": "integer",
              "format": "int32"
            }
          }
        ],
        "requestBody": {
          "content": {
            "multipart/form-data": {
              "schema": {
                "type": "object",
                "properties": {
                  "files": {
                    "type": "array",
                    "items": {
                      "type": "string",
                      "format": "binary"
                    }
                  }
                }
              },
              "encoding": {
                "files": {
                  "style": "form"
                }
              }
            }
          }
        },
        "responses": {
          "200": {
            "description": "OK"
          }
        }
      }
    },
    "/api/Teacher/DeleteMedia/media/{mediaId}": {
      "delete": {
        "tags": [
          "Teacher"
        ],
        "parameters": [
          {
            "name": "mediaId",
            "in": "path",
            "required": true,
            "schema": {
              "type": "integer",
              "format": "int32"
            }
          }
        ],
        "responses": {
          "200": {
            "description": "OK"
          }
        }
      }
    },
    "/api/Teacher/GetLiveClasses/live-classes": {
      "get": {
        "tags": [
          "Teacher"
        ],
        "responses": {
          "200": {
            "description": "OK"
          }
        }
      }
    },
    "/api/Teacher/UploadLiveClassMaterial/live-classes/{liveClassId}/material": {
      "post": {
        "tags": [
          "Teacher"
        ],
        "parameters": [
          {
            "name": "liveClassId",
            "in": "path",
            "required": true,
            "schema": {
              "type": "integer",
              "format": "int32"
            }
          }
        ],
        "requestBody": {
          "content": {
            "multipart/form-data": {
              "schema": {
                "type": "object",
                "properties": {
                  "MaterialTitle": {
                    "type": "string"
                  },
                  "MaterialDescription": {
                    "type": "string"
                  },
                  "MaterialLink": {
                    "type": "string"
                  },
                  "MaterialFile": {
                    "type": "string",
                    "format": "binary"
                  }
                }
              },
              "encoding": {
                "MaterialTitle": {
                  "style": "form"
                },
                "MaterialDescription": {
                  "style": "form"
                },
                "MaterialLink": {
                  "style": "form"
                },
                "MaterialFile": {
                  "style": "form"
                }
              }
            }
          }
        },
        "responses": {
          "200": {
            "description": "OK"
          }
        }
      }
    },
    "/api/Teacher/GetRecentExams/recent-exams": {
      "get": {
        "tags": [
          "Teacher"
        ],
        "responses": {
          "200": {
            "description": "OK"
          }
        }
      }
    },
    "/api/Teacher/GetRecentSubscribers/recent-subscribers": {
      "get": {
        "tags": [
          "Teacher"
        ],
        "responses": {
          "200": {
            "description": "OK"
          }
        }
      }
    },
    "/api/Teacher/GetTeacherSuggestions/teachergetsuggestion": {
      "get": {
        "tags": [
          "Teacher"
        ],
        "responses": {
          "200": {
            "description": "OK"
          }
        }
      }
    },
    "/api/Teacher/ReplySuggestion/reply": {
      "post": {
        "tags": [
          "Teacher"
        ],
        "requestBody": {
          "content": {
            "application/json": {
              "schema": {
                "$ref": "#/components/schemas/SuggestionReplyDto"
              }
            },
            "text/json": {
              "schema": {
                "$ref": "#/components/schemas/SuggestionReplyDto"
              }
            },
            "application/*+json": {
              "schema": {
                "$ref": "#/components/schemas/SuggestionReplyDto"
              }
            }
          }
        },
        "responses": {
          "200": {
            "description": "OK"
          }
        }
      }
    },
    "/api/Teacher/DeleteSuggestion/delete/{id}": {
      "delete": {
        "tags": [
          "Teacher"
        ],
        "parameters": [
          {
            "name": "id",
            "in": "path",
            "required": true,
            "schema": {
              "type": "integer",
              "format": "int32"
            }
          }
        ],
        "responses": {
          "200": {
            "description": "OK"
          }
        }
      }
    }
  },
  "components": {
    "schemas": {
      "ChatbotAskRequest": {
        "required": [
          "message"
        ],
        "type": "object",
        "properties": {
          "message": {
            "maxLength": 1000,
            "minLength": 2,
            "type": "string"
          },
          "history": {
            "type": "array",
            "items": {
              "$ref": "#/components/schemas/ChatbotHistoryItemDto"
            },
            "nullable": true
          }
        },
        "additionalProperties": false
      },
      "ChatbotHistoryItemDto": {
        "required": [
          "content",
          "role"
        ],
        "type": "object",
        "properties": {
          "role": {
            "maxLength": 20,
            "minLength": 0,
            "type": "string"
          },
          "content": {
            "maxLength": 1000,
            "minLength": 1,
            "type": "string"
          }
        },
        "additionalProperties": false
      },
      "Course": {
        "type": "object",
        "properties": {
          "courseId": {
            "type": "integer",
            "format": "int32"
          },
          "title": {
            "type": "string",
            "nullable": true
          },
          "description": {
            "type": "string",
            "nullable": true
          },
          "startDate": {
            "type": "string",
            "format": "date-time"
          },
          "endDate": {
            "type": "string",
            "format": "date-time"
          },
          "isPublished": {
            "type": "boolean"
          },
          "fees": {
            "type": "number",
            "format": "float"
          },
          "thumbailUrl": {
            "type": "string",
            "nullable": true
          },
          "teacherId": {
            "type": "integer",
            "format": "int32"
          },
          "createdAt": {
            "type": "string",
            "format": "date-time"
          },
          "teacher": {
            "$ref": "#/components/schemas/User"
          },
          "courseMedias": {
            "type": "array",
            "items": {
              "$ref": "#/components/schemas/CourseMedia"
            },
            "nullable": true
          }
        },
        "additionalProperties": false
      },
      "CourseMedia": {
        "type": "object",
        "properties": {
          "courseMediaId": {
            "type": "integer",
            "format": "int32"
          },
          "fileName": {
            "type": "string",
            "nullable": true
          },
          "filePath": {
            "type": "string",
            "nullable": true
          },
          "fileType": {
            "type": "string",
            "nullable": true
          },
          "courseId": {
            "type": "integer",
            "format": "int32"
          }
        },
        "additionalProperties": false
      },
      "CreateOrderRequest": {
        "type": "object",
        "properties": {
          "amount": {
            "type": "number",
            "format": "double"
          },
          "courseId": {
            "type": "integer",
            "format": "int32"
          }
        },
        "additionalProperties": false
      },
      "ExamViolationRequestDto": {
        "type": "object",
        "properties": {
          "examAttemptId": {
            "type": "integer",
            "format": "int32"
          },
          "eventType": {
            "type": "string",
            "nullable": true
          },
          "details": {
            "type": "string",
            "nullable": true
          },
          "answers": {
            "type": "array",
            "items": {
              "$ref": "#/components/schemas/SubmitExamAnswerDto"
            },
            "nullable": true
          }
        },
        "additionalProperties": false
      },
      "ForgotPasswordRequestDto": {
        "required": [
          "email"
        ],
        "type": "object",
        "properties": {
          "email": {
            "minLength": 1,
            "type": "string",
            "format": "email"
          }
        },
        "additionalProperties": false
      },
      "GoogleLoginRequestDto": {
        "required": [
          "idToken"
        ],
        "type": "object",
        "properties": {
          "idToken": {
            "minLength": 1,
            "type": "string"
          }
        },
        "additionalProperties": false
      },
      "LiveClassCreateDto": {
        "type": "object",
        "properties": {
          "courseId": {
            "type": "integer",
            "format": "int32"
          },
          "title": {
            "type": "string",
            "nullable": true
          },
          "agenda": {
            "type": "string",
            "nullable": true
          },
          "meetingLink": {
            "type": "string",
            "nullable": true
          },
          "startAt": {
            "type": "string",
            "format": "date-time"
          },
          "endAt": {
            "type": "string",
            "format": "date-time"
          }
        },
        "additionalProperties": false
      },
      "LoginRequestDto": {
        "required": [
          "emailOrUsername",
          "password"
        ],
        "type": "object",
        "properties": {
          "emailOrUsername": {
            "minLength": 1,
            "type": "string"
          },
          "password": {
            "minLength": 1,
            "type": "string"
          }
        },
        "additionalProperties": false
      },
      "RegisterRequestDto": {
        "required": [
          "email",
          "firstName",
          "lastName",
          "password"
        ],
        "type": "object",
        "properties": {
          "firstName": {
            "maxLength": 100,
            "minLength": 0,
            "type": "string"
          },
          "middleName": {
            "maxLength": 100,
            "minLength": 0,
            "type": "string",
            "nullable": true
          },
          "lastName": {
            "maxLength": 100,
            "minLength": 0,
            "type": "string"
          },
          "email": {
            "maxLength": 150,
            "minLength": 0,
            "type": "string",
            "format": "email"
          },
          "password": {
            "minLength": 8,
            "type": "string"
          },
          "phone": {
            "maxLength": 20,
            "minLength": 0,
            "type": "string",
            "format": "tel",
            "nullable": true
          },
          "role": {
            "type": "integer",
            "format": "int32"
          }
        },
        "additionalProperties": false
      },
      "ResendEmailOtpRequestDto": {
        "required": [
          "email"
        ],
        "type": "object",
        "properties": {
          "email": {
            "minLength": 1,
            "type": "string",
            "format": "email"
          }
        },
        "additionalProperties": false
      },
      "ResetPasswordRequestDto": {
        "required": [
          "email",
          "newPassword"
        ],
        "type": "object",
        "properties": {
          "email": {
            "minLength": 1,
            "type": "string",
            "format": "email"
          },
          "newPassword": {
            "minLength": 8,
            "type": "string"
          }
        },
        "additionalProperties": false
      },
      "Role": {
        "required": [
          "roleName"
        ],
        "type": "object",
        "properties": {
          "roleId": {
            "type": "integer",
            "format": "int32"
          },
          "roleName": {
            "maxLength": 50,
            "minLength": 0,
            "type": "string"
          },
          "createdAt": {
            "type": "string",
            "format": "date-time"
          }
        },
        "additionalProperties": false
      },
      "SubmitExamAnswerDto": {
        "type": "object",
        "properties": {
          "examQuestionId": {
            "type": "integer",
            "format": "int32"
          },
          "selectedOption": {
            "type": "string",
            "nullable": true
          }
        },
        "additionalProperties": false
      },
      "SubmitExamRequestDto": {
        "type": "object",
        "properties": {
          "examAttemptId": {
            "type": "integer",
            "format": "int32"
          },
          "answers": {
            "type": "array",
            "items": {
              "$ref": "#/components/schemas/SubmitExamAnswerDto"
            },
            "nullable": true
          }
        },
        "additionalProperties": false
      },
      "SuggestionCreateDto": {
        "type": "object",
        "properties": {
          "teacherId": {
            "type": "integer",
            "format": "int32"
          },
          "title": {
            "type": "string",
            "nullable": true
          },
          "message": {
            "type": "string",
            "nullable": true
          }
        },
        "additionalProperties": false
      },
      "SuggestionReplyDto": {
        "type": "object",
        "properties": {
          "id": {
            "type": "integer",
            "format": "int32"
          },
          "reply": {
            "type": "string",
            "nullable": true
          }
        },
        "additionalProperties": false
      },
      "UpdateProfileDto": {
        "type": "object",
        "properties": {
          "firstName": {
            "type": "string",
            "nullable": true
          },
          "middleName": {
            "type": "string",
            "nullable": true
          },
          "lastName": {
            "type": "string",
            "nullable": true
          },
          "email": {
            "type": "string",
            "nullable": true
          },
          "phone": {
            "type": "string",
            "nullable": true
          }
        },
        "additionalProperties": false
      },
      "User": {
        "required": [
          "email",
          "firstName",
          "lastName",
          "username"
        ],
        "type": "object",
        "properties": {
          "userId": {
            "type": "integer",
            "format": "int32"
          },
          "firstName": {
            "maxLength": 100,
            "minLength": 0,
            "type": "string"
          },
          "middleName": {
            "maxLength": 100,
            "minLength": 0,
            "type": "string",
            "nullable": true
          },
          "lastName": {
            "maxLength": 100,
            "minLength": 0,
            "type": "string"
          },
          "email": {
            "maxLength": 150,
            "minLength": 0,
            "type": "string",
            "format": "email"
          },
          "username": {
            "maxLength": 100,
            "minLength": 0,
            "type": "string"
          },
          "passwordHash": {
            "maxLength": 255,
            "minLength": 0,
            "type": "string",
            "nullable": true
          },
          "phone": {
            "maxLength": 20,
            "minLength": 0,
            "type": "string",
            "nullable": true
          },
          "profileImageUrl": {
            "maxLength": 500,
            "minLength": 0,
            "type": "string",
            "nullable": true
          },
          "roleId": {
            "type": "integer",
            "format": "int32"
          },
          "role": {
            "$ref": "#/components/schemas/Role"
          },
          "isActive": {
            "type": "boolean"
          },
          "lastLoginAt": {
            "type": "string",
            "format": "date-time",
            "nullable": true
          },
          "failedLoginAttempts": {
            "type": "integer",
            "format": "int32"
          },
          "createdAt": {
            "type": "string",
            "format": "date-time"
          },
          "updatedAt": {
            "type": "string",
            "format": "date-time",
            "nullable": true
          }
        },
        "additionalProperties": false
      },
      "UserCreateDTO": {
        "type": "object",
        "properties": {
          "firstName": {
            "type": "string",
            "nullable": true
          },
          "middleName": {
            "type": "string",
            "nullable": true
          },
          "lastName": {
            "type": "string",
            "nullable": true
          },
          "email": {
            "type": "string",
            "nullable": true
          },
          "password": {
            "type": "string",
            "nullable": true
          },
          "phone": {
            "type": "string",
            "nullable": true
          }
        },
        "additionalProperties": false
      },
      "UserUpdateDTO": {
        "type": "object",
        "properties": {
          "firstName": {
            "type": "string",
            "nullable": true
          },
          "middleName": {
            "type": "string",
            "nullable": true
          },
          "lastName": {
            "type": "string",
            "nullable": true
          },
          "email": {
            "type": "string",
            "nullable": true
          },
          "newpassword": {
            "type": "string",
            "nullable": true
          },
          "phone": {
            "type": "string",
            "nullable": true
          },
          "isActive": {
            "type": "boolean"
          }
        },
        "additionalProperties": false
      },
      "VerifyEmailOtpRequestDto": {
        "required": [
          "email",
          "otp"
        ],
        "type": "object",
        "properties": {
          "email": {
            "minLength": 1,
            "type": "string",
            "format": "email"
          },
          "otp": {
            "maxLength": 6,
            "minLength": 6,
            "type": "string"
          }
        },
        "additionalProperties": false
      },
      "VerifyForgotPasswordOtpRequestDto": {
        "required": [
          "email",
          "otp"
        ],
        "type": "object",
        "properties": {
          "email": {
            "minLength": 1,
            "type": "string",
            "format": "email"
          },
          "otp": {
            "maxLength": 6,
            "minLength": 6,
            "type": "string"
          }
        },
        "additionalProperties": false
      },
      "VerifyPaymentRequest": {
        "type": "object",
        "properties": {
          "razorpay_order_id": {
            "type": "string",
            "nullable": true
          },
          "razorpay_payment_id": {
            "type": "string",
            "nullable": true
          },
          "razorpay_signature": {
            "type": "string",
            "nullable": true
          }
        },
        "additionalProperties": false
      }
    },
    "securitySchemes": {
      "Bearer": {
        "type": "apiKey",
        "description": "JWT Authorization header using the Bearer scheme. Example: \"Authorization: Bearer {token}\"",
        "name": "Authorization",
        "in": "header"
      }
    }
  },
  "security": [
    {
      "Bearer": [ ]
    }
  ]
}